Metadata-Version: 2.1
Name: nonebot-plugin-forjyf
Version: 0.1.0
Summary: 为JYF定制的复读插件
Author: lcy
Author-email: 863109569@qq.com
Requires-Python: >=3.10,<4.0
Classifier: Programming Language :: Python :: 3
Classifier: Programming Language :: Python :: 3.10
Classifier: Programming Language :: Python :: 3.11
Requires-Dist: nonebot-adapter-onebot (>=2.2.3,<3.0.0)
Requires-Dist: nonebot2 (>=2.0.0rc4,<3.0.0)
